cfgmgr/__init__.py
cfgmgr/loaders.py
cfgmgr/manager.py
cfg_mgr-0.1.0.dist-info/LICENSE
cfg_mgr-0.1.0.dist-info/METADATA
cfg_mgr-0.1.0.dist-info/WHEEL
cfg_mgr-0.1.0.dist-info/top_level.txt
cfg_mgr-0.1.0.dist-info/RECORD
