Metadata-Version: 2.2
Name: cfg-mgr
Version: 0.1.0
Summary: Load and use configuration objects
Author-email: Raghav Jindal <raghavjindal1998@gmail.com>
License: MIT License
Project-URL: Homepage, https://github.com/raghavj98/pyconfig
Keywords: config,cfg,config file
Requires-Python: >=3.12
License-File: LICENSE
Requires-Dist: pydantic
Requires-Dist: PyYAML
